gmrde/LICENSE
gmrde/__init__.py
gmrde/umformen.py
gmrde/woerterbuch.py
gmrde/data/LICENSE
gmrde/data/german.csv
gmrde-0.1.0.dist-info/METADATA
gmrde-0.1.0.dist-info/WHEEL
gmrde-0.1.0.dist-info/top_level.txt
gmrde-0.1.0.dist-info/RECORD
