Metadata-Version: 2.1
Name: gmrde
Version: 0.1.0
Summary: Analysieren und Umformen deutscher Wörter und Sätze
Home-page: https://github.com/jarinox/python-grammar-de
Author: Jakob Stolze
Author-email: jarinox@wolke7.de
License: LGPLv2.1
Platform: UNKNOWN
Classifier: Natural Language :: German
Classifier: Programming Language :: Python :: 3
Requires-Python: >=3.6
